<?xml version="1.0" encoding="UTF-8"?>
<channel>
  <meta>
    <name>[ چه خبر؟ ]</name>
    <username>chekhabarre</username>
    <category>news</category>
    <members>259837</members>
    <profile>https://raw.githubusercontent.com/yourusername/yourrepo/main/profiles/bbcnews.png</profile>
    <telegram_link>https://t.me/chekhabarre</telegram_link>
    <generated_at>2026-05-01T12:42:03.445Z</generated_at>
  </meta>
  <posts>
    <post id="45308">
      <date>2026-05-01T12:39:29.000Z</date>
      <text>🔴 ایرنا: طرح جدید جمهوری‌اسلامی برای توافق با آمریکا به میانجیگر پاکستانی منتقل شد.</text>
      <views>892</views>
      <forwards>2</forwards>
      <media type="none"/>
    </post>
    <post id="45307">
      <date>2026-05-01T11:24:03.000Z</date>
      <text>شهر که خلوت شه قورباغه هفت‌تیر میکشه حکایت این جنگنده‌های ایرانیه که همونارم شاه ۵۰ سال پیش خرید.

@Khabariee</text>
      <views>8421</views>
      <forwards>52</forwards>
      <media type="none"/>
    </post>
    <post id="45306">
      <date>2026-05-01T11:21:05.000Z</date>
      <text>جنگنده‌های ارتش تو غرب تهران و زنجان دارن پرواز می‌کنن.</text>
      <views>8954</views>
      <forwards>37</forwards>
      <media type="none"/>
    </post>
    <post id="45305">
      <date>2026-05-01T11:08:57.000Z</date>
      <text>🔴 گاردین: دولت ترامپ، کنگره رو در بحث دریافت مجوز جنگ ایران بعد از ۶۰ روز دور زد.</text>
      <views>9918</views>
      <forwards>26</forwards>
      <media type="none"/>
    </post>
    <post id="45304">
      <date>2026-05-01T09:31:36.000Z</date>
      <text>🔴 روتونو برم.

بقائی، سخنگوی وزارت خارجه: آمریکا در زمینه رفع تحریم‌ها جدی نیست.</text>
      <views>14019</views>
      <forwards>7</forwards>
      <media type="none"/>
    </post>
    <post id="45303">
      <date>2026-05-01T08:50:31.000Z</date>
      <text>🔴 هادی چوپان: امام مجتبی خامنه‌ای پرچمدار دفاع از ایرانه.</text>
      <views>16268</views>
      <forwards>124</forwards>
      <media type="none"/>
    </post>
    <post id="45302">
      <date>2026-05-01T08:43:58.000Z</date>
      <text>🔴 فاکس نیوز: کوپر، فرمانده سنتکام، در اتاق وضعیت به رئیس‌جمهور ترامپ درباره احتمال «ضربه نهایی» به ایران گزارش داده.</text>
      <views>16062</views>
      <forwards>47</forwards>
      <media type="none"/>
    </post>
    <post id="45301">
      <date>2026-05-01T08:24:30.000Z</date>
      <text>[@OutOfContext]</text>
      <views>16118</views>
      <forwards>177</forwards>
      <media type="video" available="false">
        <mime_type>video/mp4</mime_type>
        <duration_seconds>111.062</duration_seconds>
        <note>Video not stored — view on Telegram</note>
        <telegram_link>https://t.me/chekhabarre/45301</telegram_link>
      </media>
    </post>
    <post id="45300">
      <date>2026-05-01T08:23:57.000Z</date>
      <text>🔴 بزودی میزنن.

باتوجه به صحبت‌های سناتور بلومنتال، حمله مجدد آمریکا به ایران قریب‌الوقوعه.</text>
      <views>15721</views>
      <forwards>68</forwards>
      <media type="none"/>
    </post>
    <post id="45299">
      <date>2026-05-01T08:23:53.000Z</date>
      <text>✅ کاربران محترم برای دسترسی به سایت وینکوبت فقط کافیه از طریق ربات وینکوبت وارد بشید.
🤖- @Wincobet_bot
🤖- @Wincobet_bot

📌بدون نیاز به جستجو، بدون لینک‌های پراکنده، همه چیز از طریق خود ربات انجام میشه.

📌ویژگی‌های ربات وینکوبت:👇

▪︎ورود سریع و مستقیم به سایت
▪︎دسترسی راحت از داخل تلگرام
▪︎بدون مراحل پیچیده یا ورود جداگانه

📌اگر دنبال یک راه ساده و سریع برای ورود به وینکوبت هستید، این ربات ساده‌ترین مسیر دسترسی شماست:👇
🤖- @Wincobet_bot

📌برای اطلاع از تحلیل بازی‌ها و ورود به کانال سایت جوین بدید: 👇

🔵 @Wincobetofficial</text>
      <views>15848</views>
      <forwards>10</forwards>
      <media type="photo" available="true">
        <file>img/chekhabarre__45299__photo.jpg</file>
        <width>1200</width>
        <height>1200</height>
        <telegram_link>https://t.me/chekhabarre/45299</telegram_link>
      </media>
    </post>
    <post id="45298">
      <date>2026-05-01T06:59:12.000Z</date>
      <text>میگن آمریکا دشمن خونیمونه بعد باهاش مذاکره می‌کنن و واسه فرستادن تیم فوتبالشون به این کشور دست و پا می‌شکنن.</text>
      <views>16875</views>
      <forwards>16</forwards>
      <media type="none"/>
    </post>
    <post id="45296">
      <date>2026-05-01T06:34:39.000Z</date>
      <text>🔴 مشاور وزیر ارتباطات: اینترنت پرو طرح وزارتخونه‌ی ما نبوده و این کار جرمه.</text>
      <views>17575</views>
      <forwards>30</forwards>
      <media type="none"/>
    </post>
    <post id="45295">
      <date>2026-05-01T06:00:36.000Z</date>
      <text>🔴 بزرگتونو که زدن مشتی.

نبویان، نماینده مجلس: اگر به بزرگان جمهوری‌اسلامی تعرض بشه، به هیچ کشور عربی‌ای رحم نمی‌کنیم.</text>
      <views>18253</views>
      <forwards>36</forwards>
      <media type="none"/>
    </post>
    <post id="45294">
      <date>2026-05-01T05:59:12.000Z</date>
      <text>🔴 فایننشال تایمز: اسرائیل تعداد زیادی از سامانه‌های پدافند موشکی و پهپادی خودش رو در اختیار امارات گذاشته.</text>
      <views>18130</views>
      <forwards>7</forwards>
      <media type="none"/>
    </post>
    <post id="45293">
      <date>2026-05-01T05:42:48.000Z</date>
      <text>🔴 وزیر دارایی آمریکا: درحال بررسی مسدود کردن حساب صندوق‌های بازنشستگی‌ای که حکومت ایران در خارج از کشور داره، هستیم.</text>
      <views>18302</views>
      <forwards>18</forwards>
      <media type="none"/>
    </post>
    <post id="45292">
      <date>2026-05-01T05:35:10.000Z</date>
      <text>🔴 باراک راوید، خبرنگار آکسیوس، به نقل از دو مقام ارشد آمریکایی: فرمانده فرماندهی مرکزی ارتش آمریکا (سنتکام) و ستاد مشترک ارتش آمریکا با رهبری دن کین، امشب ترامپ رو درجریان برنامه‌های عملیاتی جدیدی برای حمله احتمالی به ایران قرار دادن.</text>
      <views>18379</views>
      <forwards>24</forwards>
      <media type="none"/>
    </post>
    <post id="45291">
      <date>2026-05-01T05:31:30.000Z</date>
      <text>🔴 العربی الجدید به نقل از مقام آمریکایی: از سه‌شنبه ۷ آوریل که آتش‌بس شروع شد، هیچ تبادل آتشی بین نیروهای مسلح ایالات متحده و ایران صورت نگرفته.</text>
      <views>18452</views>
      <forwards>4</forwards>
      <media type="none"/>
    </post>
    <post id="45290">
      <date>2026-05-01T05:17:52.000Z</date>
      <text>🔴 مقام آمریکایی: ترامپ بزودی تصمیم مهمی راجب ایران می‌گیره.</text>
      <views>18778</views>
      <forwards>20</forwards>
      <media type="none"/>
    </post>
    <post id="45289">
      <date>2026-05-01T05:05:16.000Z</date>
      <text>🚨 سازمان ملل در بیانیه‌ای فوری، کوبنده و جنجالی: نگرانیم.</text>
      <views>19009</views>
      <forwards>32</forwards>
      <media type="none"/>
    </post>
    <post id="45288">
      <date>2026-05-01T05:02:55.000Z</date>
      <text>🔴 میزان سلامت عقلی خبرنگار خارجی.

- خبرنگار کاخ سفید: اگه ایران قهرمان جام جهانی بشه چیکار میکنی؟
+ ترامپ: اگه برنده بشن باید نگران این موضوع بود؛ من به جانی (رئیس فیفا) اعتماد دارم و هر کاری که از نظرش درسته، انجام بده. حالا تیمشون چطوره؟ قویه؟</text>
      <views>19140</views>
      <forwards>97</forwards>
      <media type="video" available="false">
        <mime_type>video/mp4</mime_type>
        <duration_seconds>39.744</duration_seconds>
        <note>Video not stored — view on Telegram</note>
        <telegram_link>https://t.me/chekhabarre/45288</telegram_link>
      </media>
    </post>
  </posts>
</channel>