<?xml version="1.0" encoding="UTF-8"?>
<channel>
  <meta>
    <name>[ چه خبر؟ ]</name>
    <username>chekhabarre</username>
    <category>news</category>
    <members>259837</members>
    <profile>https://raw.githubusercontent.com/yourusername/yourrepo/main/profiles/bbcnews.png</profile>
    <telegram_link>https://t.me/chekhabarre</telegram_link>
    <generated_at>2026-06-21T22:55:18.077Z</generated_at>
  </meta>
  <posts>
    <post id="49268">
      <date>2026-06-21T22:46:12.000Z</date>
      <text>منم نمیخواستم وضعیت سیاسی شه.</text>
      <views>5110</views>
      <forwards>139</forwards>
      <media type="audio" available="false">
        <mime_type>audio/mp4</mime_type>
        <note>Audio not stored — view on Telegram</note>
        <telegram_link>https://t.me/chekhabarre/49268</telegram_link>
      </media>
    </post>
    <post id="49267">
      <date>2026-06-21T22:39:01.000Z</date>
      <text>ضمنا رفقا، ما فوتبال رو سیاسی نکردیم. آقایون کردن. من‌باب اینم یه موزیک میذارم، خودم دوسش دارم.</text>
      <views>8175</views>
      <forwards>0</forwards>
      <media type="none"/>
    </post>
    <post id="49266">
      <date>2026-06-21T22:36:55.000Z</date>
      <text>ببینید از خارجی‌هایی که پرچم ج‌ا رو آوردن استادیوم و اصلاً ایرانی نیستن. اینم جالب و نوآورانه بود از سمت سپاه. بخوره در ترامپ و ونس</text>
      <views>9198</views>
      <forwards>208</forwards>
      <media type="video" available="false">
        <mime_type>video/mp4</mime_type>
        <duration_seconds>60.000999450684</duration_seconds>
        <note>Video not stored — view on Telegram</note>
        <telegram_link>https://t.me/chekhabarre/49266</telegram_link>
      </media>
    </post>
    <post id="49265">
      <date>2026-06-21T22:35:28.000Z</date>
      <text>سر صبح رضا محدث گفته بود که جمهوری اسلامی به خارجی‌ها پول داده که بیان پرچم ج‌ا رو بچرخونن. اول پیش خودم گفتم باز اینترنشنال داره کسشر میگه. الان یه ویدیو دیدم و فهمیدم که نه، ماجرا جدیه :)))))</text>
      <views>9192</views>
      <forwards>69</forwards>
      <media type="none"/>
    </post>
    <post id="49264">
      <date>2026-06-21T22:35:23.000Z</date>
      <text>Sportnavad➕ | اسپورت نود➕

⚽️ اوج هیجان مسابقات جام‌جهانی ۲۰۲۶ فقط با اسپورت نود

⚽️ گروه G جام‌جهانی ۲۰۲۶

[ مصر 🇪🇬 🆚 🇳🇿 نیوزیلند ]

⏰ بامداد دوشنبه ساعت ۰۴:۳۰
🏟 استادیوم بی‌سی پلیس

🎁   بونوس ویژه ثبت‌نام برای کاربران سایت، با شارژ حساب از طریق کریپتو ۴٪ بیشتر از مبلغ شارژ حساب دریافت کنید.

🔗 برای ورود سریعتر به اسپورت نود از طریق ربات رسمی سایت اقدام نمایید:👇

🤖 @Sportnavad_bot
🤖 @Sportnavad_bot

🔗 کانال رسمی اسپورت نود:👇

✉️ @Sportnavad</text>
      <views>9195</views>
      <forwards>0</forwards>
      <media type="photo" available="true">
        <file>img/chekhabarre__49264__photo.jpg</file>
        <width>1200</width>
        <height>1200</height>
        <telegram_link>https://t.me/chekhabarre/49264</telegram_link>
      </media>
    </post>
    <post id="49262">
      <date>2026-06-21T22:13:17.000Z</date>
      <text>کسخلا با پرچم شیروخورشید رفتن استادیوم، موقع گل زدن خوشحالی میکنن. خدایا شکرت برای ایران 🙏🏼</text>
      <views>17153</views>
      <forwards>242</forwards>
      <media type="none"/>
    </post>
    <post id="49261">
      <date>2026-06-21T21:55:15.000Z</date>
      <text>عمو تو نباید الان سر جلسه باشی؟</text>
      <views>23210</views>
      <forwards>212</forwards>
      <media type="photo" available="true">
        <file>img/chekhabarre__49261__photo.jpg</file>
        <width>831</width>
        <height>1280</height>
        <telegram_link>https://t.me/chekhabarre/49261</telegram_link>
      </media>
    </post>
    <post id="49260">
      <date>2026-06-21T21:11:49.000Z</date>
      <text>بیرانوند درکنار مسی، نمره ۱۰ گرفت از سوفا اسکور.</text>
      <views>35178</views>
      <forwards>206</forwards>
      <media type="none"/>
    </post>
    <post id="49259">
      <date>2026-06-21T21:04:27.000Z</date>
      <text>⚽️ از #فوتبال چخبر؟

تیم خایمالان جمهوری اسلامی در دومین بازی خودش در جام‌جهانی هم با بلژیک مساوی کرد.</text>
      <views>37767</views>
      <forwards>90</forwards>
      <media type="none"/>
    </post>
    <post id="49258">
      <date>2026-06-21T20:10:02.000Z</date>
      <text>🔴 عمو باز جنگ تموم شد از سوراخش پرید بیرون.

قاآنی: ای سربازان صهیونیست متجاوز و تروریست، شما در کمتر از چهار روز ۱۰۰ کشته و تلفات انسانی داده‌اید! اگر داوطلبانه از جنوب لبنان عقب‌نشینی نکنید، حماسه سال ۲۰۰۰ بار دیگر تکرار خواهد شد؛ همان سالی که با ذلت و خواری از این سرزمین فرار کردید.
و امروز نیز، اگر بر تجاوز و اشغال اصرار کنید، با ذلت و شکست از آنجا بیرون رانده خواهید شد.
خوددانید.</text>
      <views>43439</views>
      <forwards>47</forwards>
      <media type="photo" available="true">
        <file>img/chekhabarre__49258__photo.jpg</file>
        <width>1080</width>
        <height>451</height>
        <telegram_link>https://t.me/chekhabarre/49258</telegram_link>
      </media>
    </post>
    <post id="49257">
      <date>2026-06-21T20:03:42.000Z</date>
      <text>آره قرومدنگ، میتونی با اینا رفاقت کنی. بی‌آبروی کودن</text>
      <views>43350</views>
      <forwards>244</forwards>
      <media type="photo" available="true">
        <file>img/chekhabarre__49257__photo.jpg</file>
        <width>1200</width>
        <height>768</height>
        <telegram_link>https://t.me/chekhabarre/49257</telegram_link>
      </media>
    </post>
    <post id="49256">
      <date>2026-06-21T20:02:23.000Z</date>
      <text>کاری که عباس عراقچی با ونس کرد، آدم باید خدایی بگه، اسامه بن لادن با ۱۱ سپتامبر اینطور حیثیت آمریکا رو لکه‌دار نکرده بود.
دو ساعت ونس اون ور یه لنگه‌پا ایستاده بود این عاصم‌ و شهباز، عباس رو راضی کنن یه دستی، سلامی چیزی جلو دوربین با ونس داشته باشه.
عباس پیچید رفت.
خاک عالم بر سرت ونس.
عباس انتقام زلنسکی رو گرفتی.</text>
      <views>42475</views>
      <forwards>794</forwards>
      <media type="video" available="false">
        <mime_type>video/mp4</mime_type>
        <duration_seconds>62.114</duration_seconds>
        <note>Video not stored — view on Telegram</note>
        <telegram_link>https://t.me/chekhabarre/49256</telegram_link>
      </media>
    </post>
    <post id="49255">
      <date>2026-06-21T19:56:44.000Z</date>
      <text>انفجار در راس لفان قطر، دقایقی پیش.</text>
      <views>40200</views>
      <forwards>72</forwards>
      <media type="none"/>
    </post>
    <post id="49254">
      <date>2026-06-21T19:56:22.000Z</date>
      <text></text>
      <views>39911</views>
      <forwards>79</forwards>
      <media type="photo" available="true">
        <file>img/chekhabarre__49254__photo.jpg</file>
        <width>964</width>
        <height>1280</height>
        <telegram_link>https://t.me/chekhabarre/49254</telegram_link>
      </media>
    </post>
    <post id="49253">
      <date>2026-06-21T19:51:39.000Z</date>
      <text>رشید مظاهری کجاست؟</text>
      <views>39328</views>
      <forwards>148</forwards>
      <media type="photo" available="true">
        <file>img/chekhabarre__49253__photo.jpg</file>
        <width>963</width>
        <height>1280</height>
        <telegram_link>https://t.me/chekhabarre/49253</telegram_link>
      </media>
    </post>
    <post id="49252">
      <date>2026-06-21T19:51:05.000Z</date>
      <text>🔴 ترامپ: ایتالیا و نخست وزیرش پس از صرف تریلیون‌ها دلار برای ناتو، حتی فکرش را هم نمی‌کنند که با جمهوری اسلامی ایران و تهدید هسته‌ای بسیار جدی آنها درگیر شوند. دهه‌هاست که ما از آنها دفاع می‌کنیم، اما وقتی مورد آزمایش قرار می‌گیرند، آنها آنجا نیستند تا از ما و بقیه جهان دفاع کنند. خوب نیست! رئیس جمهور دونالد جی. ترامپ</text>
      <views>37773</views>
      <forwards>32</forwards>
      <media type="photo" available="true">
        <file>img/chekhabarre__49252__photo.jpg</file>
        <width>1200</width>
        <height>710</height>
        <telegram_link>https://t.me/chekhabarre/49252</telegram_link>
      </media>
    </post>
    <post id="49251">
      <date>2026-06-21T19:27:17.000Z</date>
      <text>تیم ج‌ا یه‌گل توسط طارمی زد که آفساید شد.</text>
      <views>38922</views>
      <forwards>44</forwards>
      <media type="none"/>
    </post>
    <post id="49250">
      <date>2026-06-21T18:59:58.000Z</date>
      <text></text>
      <views>40879</views>
      <forwards>115</forwards>
      <media type="video" available="false">
        <mime_type>video/mp4</mime_type>
        <duration_seconds>14.789</duration_seconds>
        <note>Video not stored — view on Telegram</note>
        <telegram_link>https://t.me/chekhabarre/49250</telegram_link>
      </media>
    </post>
    <post id="49249">
      <date>2026-06-21T18:57:08.000Z</date>
      <text>وضعیت ورزشگاه.</text>
      <views>41067</views>
      <forwards>232</forwards>
      <media type="photo" available="true">
        <file>img/chekhabarre__49249__photo.jpg</file>
        <width>1200</width>
        <height>1600</height>
        <telegram_link>https://t.me/chekhabarre/49249</telegram_link>
      </media>
    </post>
    <post id="49248">
      <date>2026-06-21T18:57:08.000Z</date>
      <text></text>
      <views>41312</views>
      <forwards>229</forwards>
      <media type="photo" available="true">
        <file>img/chekhabarre__49248__photo.jpg</file>
        <width>1200</width>
        <height>1600</height>
        <telegram_link>https://t.me/chekhabarre/49248</telegram_link>
      </media>
    </post>
  </posts>
</channel>