<?xml version="1.0" encoding="UTF-8"?>
<channel>
  <meta>
    <name>[ چه خبر؟ ]</name>
    <username>chekhabarre</username>
    <category>news</category>
    <members>259837</members>
    <profile>https://raw.githubusercontent.com/yourusername/yourrepo/main/profiles/bbcnews.png</profile>
    <telegram_link>https://t.me/chekhabarre</telegram_link>
    <generated_at>2026-05-23T10:56:38.169Z</generated_at>
  </meta>
  <posts>
    <post id="46728">
      <date>2026-05-23T10:25:32.000Z</date>
      <text>🔴 ممدباقر چرا ناناعتی؟

تصویری از دیدار امروز عاصم منیر با محمدباقر قالیباف.

@CheKhabarr</text>
      <views>6177</views>
      <forwards>32</forwards>
      <media type="photo" available="true">
        <file>img/chekhabarre__46728__photo.jpg</file>
        <width>1200</width>
        <height>610</height>
        <telegram_link>https://t.me/chekhabarre/46728</telegram_link>
      </media>
    </post>
    <post id="46727">
      <date>2026-05-23T10:14:55.000Z</date>
      <text></text>
      <views>7724</views>
      <forwards>74</forwards>
      <media type="video" available="false">
        <mime_type>video/mp4</mime_type>
        <duration_seconds>21.567</duration_seconds>
        <note>Video not stored — view on Telegram</note>
        <telegram_link>https://t.me/chekhabarre/46727</telegram_link>
      </media>
    </post>
    <post id="46726">
      <date>2026-05-23T10:14:55.000Z</date>
      <text>🔴 #اختصاصی #ارسالی_شما

امروز دانش‌آموزان شهر خرم‌آباد در استان لرستان با حضور در مقابل ساختمون آموزش و پرورش این شهر، نسبت به اقدامات آموزش و پرورش دست به تجمع اعتراضی زدن. تجمع دانش‌آموزان خرم‌آبادی با دخالت نیروهای بسیج و انتظامی به خشونت کشیده شده و نیروهای پلیس با باتوم و گاز اشک آور به بچه‌های مردم حمله کردن!
بعد از شهرکرد، حالا خرم‌آباد دومین شهریه که دانش‌آموزا توش تجمع کردن و این تجمع توسط سرکوبگرا به خشونت کشیده شده.

@CheKhabarr</text>
      <views>7725</views>
      <forwards>74</forwards>
      <media type="video" available="false">
        <mime_type>video/mp4</mime_type>
        <duration_seconds>13.934</duration_seconds>
        <note>Video not stored — view on Telegram</note>
        <telegram_link>https://t.me/chekhabarre/46726</telegram_link>
      </media>
    </post>
    <post id="46725">
      <date>2026-05-23T10:02:24.000Z</date>
      <text>🔴 العربیه: یه هیئت فنی و حقوقی پاکستانی عازم تهرانه.</text>
      <views>8939</views>
      <forwards>1</forwards>
      <media type="none"/>
    </post>
    <post id="46724">
      <date>2026-05-23T10:00:11.000Z</date>
      <text></text>
      <views>8956</views>
      <forwards>20</forwards>
      <media type="photo" available="true">
        <file>img/chekhabarre__46724__photo.jpg</file>
        <width>808</width>
        <height>1280</height>
        <telegram_link>https://t.me/chekhabarre/46724</telegram_link>
      </media>
    </post>
    <post id="46723">
      <date>2026-05-23T10:00:11.000Z</date>
      <text>🔴 شاهزاده رضا پهلوی با تعدادی از نمایندگان کنگرهٔ آمریکا از جمله دریک ون‌اُردن و دن میوزر دیدار کرد و مورد استقبال این افراد قرار گرفت؛ چارچوب کلی این گفتگوها حمایت از مردم ایران بود.

@CheKhabarr</text>
      <views>9226</views>
      <forwards>20</forwards>
      <media type="photo" available="true">
        <file>img/chekhabarre__46723__photo.jpg</file>
        <width>739</width>
        <height>1280</height>
        <telegram_link>https://t.me/chekhabarre/46723</telegram_link>
      </media>
    </post>
    <post id="46722">
      <date>2026-05-23T09:50:42.000Z</date>
      <text>[@OutOfContext]</text>
      <views>9768</views>
      <forwards>56</forwards>
      <media type="photo" available="true">
        <file>img/chekhabarre__46722__photo.jpg</file>
        <width>514</width>
        <height>800</height>
        <telegram_link>https://t.me/chekhabarre/46722</telegram_link>
      </media>
    </post>
    <post id="46721">
      <date>2026-05-23T09:05:21.000Z</date>
      <text>🔴 منابع به اسکای نیوز عربی: میانجی پاکستانی موفق شده بر مانع پرونده هسته‌ای ایران غلبه کنه!

@CheKhabarr</text>
      <views>13006</views>
      <forwards>42</forwards>
      <media type="none"/>
    </post>
    <post id="46720">
      <date>2026-05-23T08:50:18.000Z</date>
      <text>🔴 این وسط یه هواپیمای دیگه که گویا حامل یه مقام پاکستانی‌ دیگه‌س در راه تهرانه. ترانسپوندرشم خاموشه</text>
      <views>13884</views>
      <forwards>17</forwards>
      <media type="none"/>
    </post>
    <post id="46719">
      <date>2026-05-23T08:17:25.000Z</date>
      <text>🔴 بمیرم واسه کنکوریای امسال.

امروز آخرین مهلت ثبت‌نام کنکور ۱۴۰۵عه.

@CheKhabarr</text>
      <views>15927</views>
      <forwards>50</forwards>
      <media type="none"/>
    </post>
    <post id="46718">
      <date>2026-05-23T08:06:43.000Z</date>
      <text>🔴 رویترز: مذاکرات آمریکا و ایران برای پایان دادن به جنگ شدت گرفته است، اما گزارش شده که دونالد ترامپ، رئیس‌جمهور آمریکا، در صورت عدم دستیابی به توافق، به‌طور جدی در حال بررسی حملات جدید علیه ایران است.

@CheKhabarr</text>
      <views>16217</views>
      <forwards>3</forwards>
      <media type="none"/>
    </post>
    <post id="46717">
      <date>2026-05-23T08:02:13.000Z</date>
      <text>🔴 مشروب زدی پسر؟

نماینده ایران تو سازمان ملل: دولت‌های خلیج فارس موظف به جبران کامل خسارات علیه ایران هستند.

@CheKhabarr</text>
      <views>16172</views>
      <forwards>6</forwards>
      <media type="none"/>
    </post>
    <post id="46716">
      <date>2026-05-23T07:37:30.000Z</date>
      <text>🔴 Battle of The Bastards.

توئیت جدید مهاجری، عضو شورای اطلاع‌رسانی دولت، خطاب به حمید رسایی: تصمیم‌ جنگ یا صلح ربطی به نمایندگان کم سواد نداره.

@CheKhabarr</text>
      <views>17060</views>
      <forwards>69</forwards>
      <media type="photo" available="true">
        <file>img/chekhabarre__46716__photo.jpg</file>
        <width>591</width>
        <height>392</height>
        <telegram_link>https://t.me/chekhabarre/46716</telegram_link>
      </media>
    </post>
    <post id="46715">
      <date>2026-05-23T07:29:41.000Z</date>
      <text>🔴 چهار عضو کابینه ترامپ که طی سه ماه گذشته از سمت خودشون کناره‌گیری کردن یا کنار گذاشته شدن، همگی زن و دموکرات هستن که معتقدن آخوند هیچ خطری برای دنیا نداره و نباید کاری باهاش داشت.
۱- تولسی گابارد، مدیر اطلاعات ملی آمریکا.
۲- کریستی نوم، وزیر امنیت داخلی.
۳- پم باندی، وزیر دادگستری.
۴- لوری چاوز-درمر، وزیر کار.

این ۴ زن بخاطر محکوم کردن جنگ با آخوند، یا اخراج شدن و یا استعفا دادن.

@CheKhabarr</text>
      <views>16545</views>
      <forwards>38</forwards>
      <media type="none"/>
    </post>
    <post id="46714">
      <date>2026-05-23T07:29:39.000Z</date>
      <text>رسانه‌های حکومتی این عکس رو با عنوان «متن دست‌نویس شهید امیرعبداللهیان برای سخنرانی ۲۲ بهمن» منتشر کردن؛ شما فقط دست‌خط و سطح سواد وزیر خارجه سابق جمهوری‌اسلامی رو ببین :)))

@Khabariee</text>
      <views>14836</views>
      <forwards>118</forwards>
      <media type="photo" available="true">
        <file>img/chekhabarre__46714__photo.jpg</file>
        <width>1200</width>
        <height>1695</height>
        <telegram_link>https://t.me/chekhabarre/46714</telegram_link>
      </media>
    </post>
    <post id="46713">
      <date>2026-05-23T07:29:31.000Z</date>
      <text>‼️ اگه هنوز داری تو این اوضاع اینترنت داری دستی دنبال ورود به سایت می‌گردی یعنی عملاً داری زمان رو از دست میدی.

♨️ کاربران حرفه‌ای مستقیم وارد سایت میشن.

و این مسیر از اینجا شروع میشه:👇

🤖 @Wincobet_bot
🤖 @Wincobet_bot
⚡️بدون لینک‌های فیک
⚡️بدون پیچیدگی
⚡️بدون معطلی اضافه

📌چیزی که ساده به نظر میاد، دقیقاً همون چیزیه که کاربران حرفه‌ای‌ها دنبالش هستن:👇

🤖 @Wincobet_bot

📌کانال رسمی وینکوبت:

🔵 @Wincobetofficial</text>
      <views>15254</views>
      <forwards>1</forwards>
      <media type="photo" available="true">
        <file>img/chekhabarre__46713__photo.jpg</file>
        <width>1200</width>
        <height>1200</height>
        <telegram_link>https://t.me/chekhabarre/46713</telegram_link>
      </media>
    </post>
    <post id="46712">
      <date>2026-05-23T07:19:45.000Z</date>
      <text>به شخصه از بازیکنای تیم ملی فوتبال آخوند بیشتر از اون بسیجی‌ای که کف خیابونه متنفرم. میزان حرومزادگی این نسل فوتبال ایران یه مورد نادر تاریخیه</text>
      <views>15154</views>
      <forwards>11</forwards>
      <media type="none"/>
    </post>
    <post id="46711">
      <date>2026-05-23T07:18:06.000Z</date>
      <text>🔴 غیررسمی: آمریکا درخواست ویزای شجاع خلیل‌زاده، مهدی طارمی و احسان حاج‌صفی رو رد کرد و این سه نماینده‌ی سپاه پاسداران تو تیم فوتبال آخوند، اجازهٔ بازی تو جام جهانی رو نخواهند داشت.

@CheKhabarr</text>
      <views>15552</views>
      <forwards>121</forwards>
      <media type="none"/>
    </post>
    <post id="46710">
      <date>2026-05-23T07:12:47.000Z</date>
      <text>🔴 امتحانات پایان ترم دانشگاه‌های پیام نور مجازی شد.

@CheKhabarr</text>
      <views>15885</views>
      <forwards>22</forwards>
      <media type="none"/>
    </post>
    <post id="46709">
      <date>2026-05-23T06:36:22.000Z</date>
      <text>🔴 قضیه ناموسی شد.

منابع غربی تأیید می‌کنن که جمهوری‌اسلامی از طریق بازوهاش قصد ترور دختر ترامپ رو داشته.

@CheKhabarr</text>
      <views>17711</views>
      <forwards>89</forwards>
      <media type="none"/>
    </post>
  </posts>
</channel>