<?xml version="1.0" encoding="UTF-8"?>
<channel>
  <meta>
    <name>[ چه خبر؟ ]</name>
    <username>chekhabarre</username>
    <category>news</category>
    <members>259837</members>
    <profile>https://raw.githubusercontent.com/yourusername/yourrepo/main/profiles/bbcnews.png</profile>
    <telegram_link>https://t.me/chekhabarre</telegram_link>
    <generated_at>2026-06-04T21:02:42.394Z</generated_at>
  </meta>
  <posts>
    <post id="47530">
      <date>2026-06-04T20:51:15.000Z</date>
      <text>قیصر مادرجنده هم امشب تو تجمعات شبانه بسیجیا تو تهران کنسرت لایو گذاشته. این جنگ یکی از خوبیاش این بود که جنده بودن مادر خیلیا عین جوش چرکی زد بیرون.</text>
      <views>7160</views>
      <forwards>104</forwards>
      <media type="video" available="false">
        <mime_type>video/mp4</mime_type>
        <duration_seconds>91</duration_seconds>
        <note>Video not stored — view on Telegram</note>
        <telegram_link>https://t.me/chekhabarre/47530</telegram_link>
      </media>
    </post>
    <post id="47529">
      <date>2026-06-04T20:49:11.000Z</date>
      <text>مردم عزیز کوبا کونو سفت بچسبید که ترامپ قراره آزادی برای شما هم بیاره.</text>
      <views>9182</views>
      <forwards>36</forwards>
      <media type="none"/>
    </post>
    <post id="47528">
      <date>2026-06-04T20:45:42.000Z</date>
      <text>🔴 Mojtaba, The professional.

خبرنگار: خشم حماسی پدر، همسر و فرزند مجتبی خامنه‌ای رو کشته.

ترامپ: اون احتمالا منو دوست نداره، اما بنظرم او یک شخصیت حرفه‌ایه.</text>
      <views>11221</views>
      <forwards>106</forwards>
      <media type="none"/>
    </post>
    <post id="47527">
      <date>2026-06-04T20:43:03.000Z</date>
      <text>اینم از طهلیل امشب.</text>
      <views>12245</views>
      <forwards>0</forwards>
      <media type="none"/>
    </post>
    <post id="47526">
      <date>2026-06-04T20:41:50.000Z</date>
      <text>خنده داره داداش

پلن ترامپ این بود احمدی‌نژاد رو رئیس جمهور دوره‌ گذار کنه حتی محافظای دورشم زد که تو زندون خانگی بود ولی وسط راه وا داد وقتی دید قضیه جدیه 

بعد شماها هنوز منتظرین جنگ شه جمهوری اسلامی شکست بخوره پسر شاه بیاد 

پسر شاه این‌ وسط نخودی بود</text>
      <views>13249</views>
      <forwards>37</forwards>
      <media type="none"/>
    </post>
    <post id="47525">
      <date>2026-06-04T20:35:18.000Z</date>
      <text>پلنی دارید یه ۴ تا سرباز کونی غربی بکشیم این جنگ کیری شروع شه یا نه؟</text>
      <views>15124</views>
      <forwards>86</forwards>
      <media type="none"/>
    </post>
    <post id="47524">
      <date>2026-06-04T20:31:28.000Z</date>
      <text>🔴 ترامپ: اگه سربازان آمریکایی کشته شن، جنگ رو از سر میگیریم.</text>
      <views>16521</views>
      <forwards>116</forwards>
      <media type="none"/>
    </post>
    <post id="47523">
      <date>2026-06-04T20:23:22.000Z</date>
      <text>🔴 دارک شد که.

ترامپ: چین یه کارهایی با ما می‌کنه و ماهم با اونا کارهایی می‌کنیم.

@CheKhabarr</text>
      <views>19763</views>
      <forwards>71</forwards>
      <media type="none"/>
    </post>
    <post id="47522">
      <date>2026-06-04T19:42:46.000Z</date>
      <text>🔴 به تو نمی‌رسه گوه مردم ایرانو بخوری مشتی.

پوتین: مردم ایران نشون دادن که متحدن و برای دفاع از کشورشون ایستادن.

@CheKhabarr</text>
      <views>26195</views>
      <forwards>31</forwards>
      <media type="none"/>
    </post>
    <post id="47521">
      <date>2026-06-04T19:24:12.000Z</date>
      <text>🔴 نه فقط تو اسرائیل؛ بلکه آمریکا در سراسر خاورمیانه سطح هشدار رو افزایش داده.</text>
      <views>28845</views>
      <forwards>186</forwards>
      <media type="none"/>
    </post>
    <post id="47520">
      <date>2026-06-04T18:27:40.000Z</date>
      <text>🔴کانال ۱۲ اسرائیل: پیشرفتی در مذاکرات بین ایران و ایالات متحده حاصل نشده.
واشنگتن از تهران خواسته است پاسخ خود را تا پایان هفته ارائه دهد.</text>
      <views>33321</views>
      <forwards>95</forwards>
      <media type="none"/>
    </post>
    <post id="47519">
      <date>2026-06-04T18:23:16.000Z</date>
      <text>حملات اسرائیل به لبنان امروزم ادامه داشت.</text>
      <views>33399</views>
      <forwards>23</forwards>
      <media type="video" available="false">
        <mime_type>video/mp4</mime_type>
        <duration_seconds>7.184</duration_seconds>
        <note>Video not stored — view on Telegram</note>
        <telegram_link>https://t.me/chekhabarre/47519</telegram_link>
      </media>
    </post>
    <post id="47518">
      <date>2026-06-04T17:03:13.000Z</date>
      <text>⚽ از #فوتبال چه‌خبر؟!

تیزر به‌شدت پشم‌ریزون و محشر نایکی به مناسبت جام‌جهانی با حضور تعداد زیادی از ستاره‌های دنیای فوتبال و چندتا سلبریتی دیگه منتشر شد.

- ارزش دانلود و دیدن ۱۰۰ از ۱۰

@CheKhabarr</text>
      <views>38095</views>
      <forwards>1560</forwards>
      <media type="video" available="false">
        <mime_type>video/mp4</mime_type>
        <duration_seconds>360</duration_seconds>
        <note>Video not stored — view on Telegram</note>
        <telegram_link>https://t.me/chekhabarre/47518</telegram_link>
      </media>
    </post>
    <post id="47517">
      <date>2026-06-04T16:14:25.000Z</date>
      <text>دوتا پست تو چنل دوممون زدیم که خوندنش جیگر هر آدمیو خون می‌کنه. از وقتی خوندمش تا لحظه‌ای که نوشتمش و پستش کردم دستام می‌لرزید. اگر دل و دماغشو دارید این دوتا پست که لینکشونو این زیر میذارمو به ترتیب بخونید تا ببینید تو این مملکت چه شیاطینی همراه با ما دارن زندگی می‌کنن.

پست اول
پست دوم</text>
      <views>37259</views>
      <forwards>105</forwards>
      <media type="none"/>
    </post>
    <post id="47516">
      <date>2026-06-04T15:34:22.000Z</date>
      <text>این سری نوبت ماهاس که از شما بپرسیم، با آقا چه نسبتی دارین؟</text>
      <views>37307</views>
      <forwards>2</forwards>
      <media type="none"/>
    </post>
    <post id="47515">
      <date>2026-06-04T15:18:34.000Z</date>
      <text>🔴 دست خدا عیان شد.

حداد عادل: آقای جدیدمون از آقای قدیممون سختگیرتره.

@CheKhabarr</text>
      <views>38200</views>
      <forwards>81</forwards>
      <media type="none"/>
    </post>
    <post id="47514">
      <date>2026-06-04T15:16:59.000Z</date>
      <text>🔴 سردار قاآنی: باید کاری کنیم که اسرائیل به نقطهٔ قبل از جنگ ۴۰ روزه عقب نشینی کنه.

@CheKhabarr</text>
      <views>37827</views>
      <forwards>11</forwards>
      <media type="none"/>
    </post>
    <post id="47513">
      <date>2026-06-04T15:15:42.000Z</date>
      <text>🎧 از #رپفارسی چه‌خبر؟!

ویدئویی از حصین، رپر رپفارسی، منتشر شده که توش کف مونیخ داره نوحه گوش می‌ده. فدایی چه شناختی رو این داشت که ۵ سال پیش بهش می‌گفت قند پخش کنِ بچه‌هیئتی :)))

@CheKhabarr</text>
      <views>38623</views>
      <forwards>495</forwards>
      <media type="video" available="false">
        <mime_type>video/mp4</mime_type>
        <duration_seconds>11.967</duration_seconds>
        <note>Video not stored — view on Telegram</note>
        <telegram_link>https://t.me/chekhabarre/47513</telegram_link>
      </media>
    </post>
    <post id="47512">
      <date>2026-06-04T15:15:34.000Z</date>
      <text>▪︎ اگه این روزا سایتا سخت لود میشن، ربات تلگرام وینکوبت خیلی کارو راحت کرده:👇

🤖 @Wincobet_bot

بدون اینکه از تلگرام خارج شی میتونی مستقیم وارد بخش بازی‌ها و کازینو بشی، پیش‌بینی ثبت کنی و حتی واریز و برداشت انجام بدی.
▪︎حالت Mini App داخل تلگرامه و خیلی سبک‌تر و سریع‌تر باز میشه:👇

🤖 @Wincobet_bot</text>
      <views>36266</views>
      <forwards>0</forwards>
      <media type="video" available="false">
        <mime_type>video/mp4</mime_type>
        <duration_seconds>34.027</duration_seconds>
        <note>Video not stored — view on Telegram</note>
        <telegram_link>https://t.me/chekhabarre/47512</telegram_link>
      </media>
    </post>
    <post id="47511">
      <date>2026-06-04T15:12:46.000Z</date>
      <text>🔴 خوش‌چشم، کارشناس صداوسیما: بنظرم دیگه جنگ نمی‌شه چون دشمنان ازمون می‌ترسن.

@CheKhabarr</text>
      <views>36781</views>
      <forwards>66</forwards>
      <media type="none"/>
    </post>
  </posts>
</channel>