<?xml version="1.0" encoding="UTF-8"?>
<channel>
  <meta>
    <name>[ چه خبر؟ ]</name>
    <username>chekhabarre</username>
    <category>news</category>
    <members>259837</members>
    <profile>https://raw.githubusercontent.com/yourusername/yourrepo/main/profiles/bbcnews.png</profile>
    <telegram_link>https://t.me/chekhabarre</telegram_link>
    <generated_at>2026-06-05T22:05:29.957Z</generated_at>
  </meta>
  <posts>
    <post id="47580">
      <date>2026-06-05T21:52:40.000Z</date>
      <text>🔴 برو مادرقهبه.

ترامپ: ایران بین ۲۱-۲۲ درصد موشک‌های خودش رو دراختیار‌ داره.</text>
      <views>7374</views>
      <forwards>17</forwards>
      <media type="none"/>
    </post>
    <post id="47578">
      <date>2026-06-05T21:23:30.000Z</date>
      <text>🔴 خفه مادرقهبه.

ترامپ: مسئله ایران یا از طریق توافق اوکی می‌شه یا اقدام نظامی.</text>
      <views>18275</views>
      <forwards>85</forwards>
      <media type="none"/>
    </post>
    <post id="47577">
      <date>2026-06-05T21:19:31.000Z</date>
      <text>🔴 شین | انفجار و فعالیت پدافند هوایی در جزیره خارگ، استان بوشهر،</text>
      <views>20110</views>
      <forwards>188</forwards>
      <media type="none"/>
    </post>
    <post id="47576">
      <date>2026-06-05T21:17:16.000Z</date>
      <text>باز ساعت یک شد و شروع کردین به کسشر</text>
      <views>20789</views>
      <forwards>43</forwards>
      <media type="none"/>
    </post>
    <post id="47575">
      <date>2026-06-05T20:46:29.000Z</date>
      <text>🔴 ای خای...

نخست وزیر پاکستان: همواره کنار آمریکا بودیم و برای همیشه از ترامپ به عنوان مرد صلح یاد میکنیم.

@CheKhabarr</text>
      <views>25878</views>
      <forwards>32</forwards>
      <media type="video" available="false">
        <mime_type>video/mp4</mime_type>
        <duration_seconds>61.803</duration_seconds>
        <note>Video not stored — view on Telegram</note>
        <telegram_link>https://t.me/chekhabarre/47575</telegram_link>
      </media>
    </post>
    <post id="47574">
      <date>2026-06-05T20:38:02.000Z</date>
      <text>🔴 امشب برنامه «خیابان انقلاب» طبق روال خودش پخش نشده. و دلیل پخش نشدنش هم حرفای این بابا بوده. ببینید حتما</text>
      <views>27855</views>
      <forwards>526</forwards>
      <media type="video" available="false">
        <mime_type>video/mp4</mime_type>
        <duration_seconds>83.105</duration_seconds>
        <note>Video not stored — view on Telegram</note>
        <telegram_link>https://t.me/chekhabarre/47574</telegram_link>
      </media>
    </post>
    <post id="47573">
      <date>2026-06-05T19:58:22.000Z</date>
      <text>🔴 گزارش منابع عراقی از انفجار تو اطراف سفارت ج.ا تو سلیمانیه عراق.</text>
      <views>32151</views>
      <forwards>51</forwards>
      <media type="none"/>
    </post>
    <post id="47572">
      <date>2026-06-05T19:54:12.000Z</date>
      <text>ترامپ: همین الانم داریم با ایران گفتگو می‌کنیم.</text>
      <views>32985</views>
      <forwards>41</forwards>
      <media type="none"/>
    </post>
    <post id="47571">
      <date>2026-06-05T19:38:32.000Z</date>
      <text>🔴 عمو مادرتو گاییدم.

ترامپ: اوضاع با ایران عالی پیش می‌ره.</text>
      <views>36055</views>
      <forwards>123</forwards>
      <media type="none"/>
    </post>
    <post id="47570">
      <date>2026-06-05T18:37:52.000Z</date>
      <text>🔴 اکسیوس: استیو ویتکاف و جرد کوشنر روز پنجشنبه برای رایزنی با گروهی از کارشناسان فنی که ممکنه تو مذاکرات هسته‌ای با ایران نقش داشته باشن، به آزمایشگاه ملی اوک ریج تو ایالت تنسی سفر کردن. این می‌تونه نشانه‌ای ازین باشه که مذاکرات ایران و آمریکا وارد مقطع حساس و مثبتی شده و شانس به نتیجه رسیدنش وجود داره.

@CheKhabarr</text>
      <views>39568</views>
      <forwards>34</forwards>
      <media type="none"/>
    </post>
    <post id="47569">
      <date>2026-06-05T17:54:35.000Z</date>
      <text>🔴 ترامپ: ما در برابر ایران موفقیت‌های بزرگی کسب کرده‌ایم. آنها در موقعیتی نیستند که سلاح هسته‌ای داشته باشند.</text>
      <views>41202</views>
      <forwards>10</forwards>
      <media type="none"/>
    </post>
    <post id="47568">
      <date>2026-06-05T17:48:10.000Z</date>
      <text>هیچوقت فکرشو نمی‌کردم با متن تبلیغات فیک فیلم سوپر تو کانالای تلگرامی حال کنم تا اینکه شاهکاری مثل «فووووری فیلم تجاوز گروهی به محمدرضا شهبازی چه خشن ترتیبشو میدن صدای ناله‌ش میاد قشنگ 🥺😳🥵😳😈🔞» رو دیدم.</text>
      <views>42051</views>
      <forwards>402</forwards>
      <media type="none"/>
    </post>
    <post id="47567">
      <date>2026-06-05T16:29:01.000Z</date>
      <text>🔴 تورو میبردن مذاکره بسته بودیما.

محسن رضایی: مذاکرات متوقف شده؛ آمریکا اگه توافق میخواد باید فورا ۲۴ میلیارد دلار دارایی‌های ایران رو آزاد کنه.

@CheKhabarr</text>
      <views>43157</views>
      <forwards>45</forwards>
      <media type="none"/>
    </post>
    <post id="47565">
      <date>2026-06-05T16:20:24.000Z</date>
      <text>🔴 ناناعت شودم.

مقام ایرانی به سی‌ان‌ان: آقا مجتبی خامنه‌ای با ترامپ قمارباز دیدار نمی‌کنه.</text>
      <views>42865</views>
      <forwards>32</forwards>
      <media type="none"/>
    </post>
    <post id="47564">
      <date>2026-06-05T15:33:59.000Z</date>
      <text>برسد به دست محمدرضا شهبازی.</text>
      <views>45402</views>
      <forwards>400</forwards>
      <media type="photo" available="true">
        <file>img/chekhabarre__47564__photo.jpg</file>
        <width>949</width>
        <height>1280</height>
        <telegram_link>https://t.me/chekhabarre/47564</telegram_link>
      </media>
    </post>
    <post id="47563">
      <date>2026-06-05T15:28:26.000Z</date>
      <text>🔴 کاش میزان ارتباط منم با خاورمیانه در حد شهروند آلمانی بود.

آلمان به شهرونداش درباره سفر به بحرین و کویت بخاطز وضعیت امنیتی «بسیار ناپایدار» تو منطقه هشدار داد.

@CheKhabarr</text>
      <views>41499</views>
      <forwards>21</forwards>
      <media type="none"/>
    </post>
    <post id="47562">
      <date>2026-06-05T15:28:20.000Z</date>
      <text>طبق اطلاعات شهروندخبرنگاران؛قیمت‌هایی که در شب‌های اول پرداخت می‌شده طبق آماری که این فاحشه‌های ولایی داده بودند برای برادران حشدالشعبی و فاطمیون و زینبیون بین ۵ تا ٧ میلیون و برای مزدوران بسیجی و سپاهی بین ٢ تا ۴ میلیون تومان بهمراه یک کارت هدیه بوده است.
ولی در این شبهایی که از تب و تاب افتاده‌ است؛ اینها که زمانی در متل قو و دبی و مشهد درآمدهای بالایی داشتند حاضر به صیغه‌‌های یکهفته‌ای؛یکماهه و البته در اکثر موارد به صیغه‌‌های ساعتی با دریافتی بسیار بسیار پایین هم راضی شده‌اند.

-Live Iran-
@Khabariee</text>
      <views>37939</views>
      <forwards>434</forwards>
      <media type="video" available="false">
        <mime_type>video/mp4</mime_type>
        <duration_seconds>86.17</duration_seconds>
        <note>Video not stored — view on Telegram</note>
        <telegram_link>https://t.me/chekhabarre/47562</telegram_link>
      </media>
    </post>
    <post id="47561">
      <date>2026-06-05T15:27:47.000Z</date>
      <text>Sportnavad➕ | اسپورت نود➕

🇫🇷 دیدار جذاب و حساس نیمه‌نهایی رولان‌گاروس بین ماتئو آرنالدی و فلاویو کوبولی رو با آپشن‌های مختلف در اسپورت نود پیش‌بینی کنید.

🔗 ضرایب رقابتی و متنوع فقط در سایت معتبر اسپورت نود به همراه:👇

شارژ از طریق کریپتو
واریز و برداشت سریع
پشتیبانی ۲۴ ساعته
کازینو آنلاین و بازی انفجار
پیش‌بینی زنده تمامی مسابقات
🎁 بونوس ویژه ثبت‌نام برای کاربران سایت، با شارژ حساب از طریق کریپتو ۴٪ بیشتر از مبلغ شارژ حساب دریافت کنید.

🔗 برای ورود سریعتر به اسپورت نود از طریق ربات رسمی سایت اقدام نمایید:👇

🤖 @Sportnavad_bot
🤖 @Sportnavad_bot

🔗 کانال رسمی اسپورت نود:👇

✉️ @Sportnavad</text>
      <views>37753</views>
      <forwards>0</forwards>
      <media type="photo" available="true">
        <file>img/chekhabarre__47561__photo.jpg</file>
        <width>1200</width>
        <height>1200</height>
        <telegram_link>https://t.me/chekhabarre/47561</telegram_link>
      </media>
    </post>
    <post id="47560">
      <date>2026-06-05T15:15:25.000Z</date>
      <text>بیانیه قدیمی بوده و کاخ سفید تکذیب کرد.</text>
      <views>37156</views>
      <forwards>21</forwards>
      <media type="none"/>
    </post>
    <post id="47559">
      <date>2026-06-05T14:39:54.000Z</date>
      <text>🔴 فحش ناموسی.

کاخ سفید: این گفتگوها بسیار مثبت و سازنده بودند و ایالات متحده عمیقاً از سلطنت عمان بابت حمایت از این ابتکار قدردانی می‌کند. فرستاده ویژه ویتکاف به دکتر عراقچی تأکید کرد که از سوی رئیس‌جمهور ترامپ مأموریت دارد در صورت امکان، اختلافات میان دو کشور را از طریق گفت‌وگو و دیپلماسی حل‌وفصل کند. 
این موضوعات بسیار پیچیده هستند و ارتباط مستقیم امروز فرستاده ویژه ویتکاف گامی رو به جلو در جهت دستیابی به نتیجه‌ای دوجانبه و سودمند بوده است. طرفین توافق کردند که شنبه آینده دوباره دیدار کنند.

@CheKhabarr</text>
      <views>39758</views>
      <forwards>52</forwards>
      <media type="none"/>
    </post>
  </posts>
</channel>