<?xml version="1.0" encoding="UTF-8"?>
<channel>
  <meta>
    <name>[ چه خبر؟ ]</name>
    <username>chekhabarre</username>
    <category>news</category>
    <members>259837</members>
    <profile>https://raw.githubusercontent.com/yourusername/yourrepo/main/profiles/bbcnews.png</profile>
    <telegram_link>https://t.me/chekhabarre</telegram_link>
    <generated_at>2026-05-04T07:29:15.250Z</generated_at>
  </meta>
  <posts>
    <post id="45461">
      <date>2026-05-04T07:11:04.000Z</date>
      <text>چندسال پیش اون موقع که ج.ا کشتی آمریکایی رو توقیف کرد و سربازاش رو به اسارت گرفت یادتونه چه حماسه‌سازی‌ای کرده بود؟ صداوسیما هر ثانیه بصورت لایو از اون سربازا فیلم و مستند می‌ساخت و پخش می‌کرد.
حالا آمریکا دو هفته‌س ۲۲ نیروی ایرانی رو اسیر کرده و حتی یه‌دونه تصویر تحقیرآمیزم ازشون پخش نکرده.
شما فقط تفاوت رو ببینید.</text>
      <views>3640</views>
      <forwards>48</forwards>
      <media type="none"/>
    </post>
    <post id="45460">
      <date>2026-05-04T07:02:36.000Z</date>
      <text>🔴 پاکستان: آمریکا ۲۲ خدمه کشتی ایرانی توقیف شده رو تحویل پاکستان داده و ما اونارو به ایران می‌فرستیم.</text>
      <views>4745</views>
      <forwards>16</forwards>
      <media type="none"/>
    </post>
    <post id="45459">
      <date>2026-05-04T06:29:06.000Z</date>
      <text>میدیدم دور گردنا طناب، سیاست لب‌حوضی، وعده‌ها باد هوا
نه شب ظلمت رفت، نه اومده صبح امید
غروب جمعه بودیم با حال خراب</text>
      <views>7756</views>
      <forwards>40</forwards>
      <media type="none"/>
    </post>
    <post id="45458">
      <date>2026-05-04T06:18:23.000Z</date>
      <text>🔴 تو کلاً حساب نیستی مرتیکه زن‌ذلیل.

مکرون: ما در طرح جدید آمریکا درباره تنگه هرمز مشارکت نخواهیم کرد.</text>
      <views>8751</views>
      <forwards>8</forwards>
      <media type="none"/>
    </post>
    <post id="45457">
      <date>2026-05-04T05:53:12.000Z</date>
      <text>🔴 کانال ۱۲ اسرائیل: واشنگتن به اسرائیل اطلاع داده که آتش‌بس با لبنان همچنان باید ادامه داشته باشه.</text>
      <views>10318</views>
      <forwards>7</forwards>
      <media type="none"/>
    </post>
    <post id="45456">
      <date>2026-05-04T05:40:06.000Z</date>
      <text>🔴 منابع عبری: نتانیاهو امشب یه جلسه امنیتی محدود در رابطه با ایران تشکیل می‌ده.</text>
      <views>11053</views>
      <forwards>8</forwards>
      <media type="none"/>
    </post>
    <post id="45455">
      <date>2026-05-04T05:10:37.000Z</date>
      <text>⚫ مهدی رسولی و محمدرضا میری، دو معترض مشهدی بازداشت شده تو اعتراضات شب‌های ۱۸ و ۱۹ دی هم توسط جمهوری‌اسلامی اعدام شدن.</text>
      <views>12805</views>
      <forwards>61</forwards>
      <media type="none"/>
    </post>
    <post id="45454">
      <date>2026-05-04T05:08:06.000Z</date>
      <text>⚫ ابراهیم دولت‌آبادی از بازداشتی‌های اعتراضات دی‌ماه در شهر مشهد، توسط جمهوری‌اسلامی اعدام شد.</text>
      <views>12539</views>
      <forwards>53</forwards>
      <media type="none"/>
    </post>
    <post id="45453">
      <date>2026-05-04T04:05:07.000Z</date>
      <text>🔴 ساعاتی پیش یه نفتکش تو فاصله ۷۸ مایل دریایی شمال فجیره امارات، مورد اصابت یه پرتابه‌ ناشناس قرار گرفته.</text>
      <views>14549</views>
      <forwards>28</forwards>
      <media type="none"/>
    </post>
    <post id="45452">
      <date>2026-05-03T22:37:15.000Z</date>
      <text>G(old)</text>
      <views>19972</views>
      <forwards>9</forwards>
      <media type="none"/>
    </post>
    <post id="45451">
      <date>2026-05-03T22:37:07.000Z</date>
      <text>[@OutOfContext]</text>
      <views>19332</views>
      <forwards>117</forwards>
      <media type="photo" available="true">
        <file>img/chekhabarre__45451__photo.jpg</file>
        <width>1080</width>
        <height>669</height>
        <telegram_link>https://t.me/chekhabarre/45451</telegram_link>
      </media>
    </post>
    <post id="45450">
      <date>2026-05-03T22:37:05.000Z</date>
      <text>✅ کاربران محترم برای دسترسی به سایت وینکوبت فقط کافیه از طریق ربات وینکوبت وارد بشید.
🤖- @Wincobet_bot
🤖- @Wincobet_bot

📌بدون نیاز به جستجو، بدون لینک‌های پراکنده، همه چیز از طریق خود ربات انجام میشه.

📌ویژگی‌های ربات وینکوبت:👇

▪︎ورود سریع و مستقیم به سایت
▪︎دسترسی راحت از داخل تلگرام
▪︎بدون مراحل پیچیده یا ورود جداگانه

📌اگر دنبال یک راه ساده و سریع برای ورود به وینکوبت هستید، این ربات ساده‌ترین مسیر دسترسی شماست:👇
🤖- @Wincobet_bot

📌برای اطلاع از تحلیل بازی‌ها و ورود به کانال سایت جوین بدید: 👇

🔵 @Wincobetofficial</text>
      <views>19614</views>
      <forwards>1</forwards>
      <media type="photo" available="true">
        <file>img/chekhabarre__45450__photo.jpg</file>
        <width>1200</width>
        <height>1200</height>
        <telegram_link>https://t.me/chekhabarre/45450</telegram_link>
      </media>
    </post>
    <post id="45449">
      <date>2026-05-03T22:35:46.000Z</date>
      <text>🔴ابراهیم عزیزی، رئیس کمیسیون امنیت‌ملی مجلس:
هشدار.
هرگونه دخالت آمریکایی‌ها در نظام جدید دریایی تنگه هرمز به عنوان نقض آتش‌بس تلقی خواهد شد.
تنگه‌هرمز و خلیج‌فارس توسط پست‌های توهمی ترامپ مدیریت نخواهند شد!
هیچ‌کس سناریوهای بازی مقصر را باور نخواهد کرد!

@CheKhabarr</text>
      <views>18727</views>
      <forwards>43</forwards>
      <media type="photo" available="true">
        <file>img/chekhabarre__45449__photo.jpg</file>
        <width>1200</width>
        <height>622</height>
        <telegram_link>https://t.me/chekhabarre/45449</telegram_link>
      </media>
    </post>
    <post id="45448">
      <date>2026-05-03T21:29:26.000Z</date>
      <text>اینو نمی‌دونم اما اگه سپاه، آتیش اول رو به‌سمت کشتی‌های آمریکایی بیافروزه، احتمال اینکه دیگه به مجوز کنگره هم برای شروع مجدد درگیری نیاز نباشه هست.
ضمناً ماجرای محاصره هم نامعلومه</text>
      <views>20868</views>
      <forwards>144</forwards>
      <media type="none"/>
    </post>
    <post id="45447">
      <date>2026-05-03T21:24:42.000Z</date>
      <text>زیربار عبور کشتی‌ها برن که شعار هفتاد روزه کنترل تنگه‌هرمز زیرسوال میره؛ زیربار نرن که یعنی شروع درگیری.
کیش، مات.</text>
      <views>21199</views>
      <forwards>245</forwards>
      <media type="none"/>
    </post>
    <post id="45446">
      <date>2026-05-03T21:17:21.000Z</date>
      <text>عجب سیاستمداریه این؛ عملا با این حرکت هم تنگه باز می‌شه و هم اگه سپاه حرکتی بزنه انگشت اشاره دنیا میره سمت جمهوری اسلامی.</text>
      <views>21246</views>
      <forwards>223</forwards>
      <media type="none"/>
    </post>
    <post id="45445">
      <date>2026-05-03T20:49:17.000Z</date>
      <text>من کاملاً آگاه هستم که نمایندگان من در حال گفتگوهای بسیار مثبتی با کشور ایران هستند و این گفتگوها می‌تواند به چیزی بسیار مثبت برای همه منجر شود. جنبش کشتی صرفاً برای آزاد کردن افراد، شرکت‌ها و کشورهایی است که مطلقاً هیچ کار اشتباهی انجام نداده‌اند - آنها قربانی شرایط هستند. این یک اقدام بشردوستانه از طرف ایالات متحده، کشورهای خاورمیانه، اما به ویژه کشور ایران است. بسیاری از این کشتی‌ها با کمبود غذا و هر چیز دیگری که برای خدمه بزرگ لازم است تا به صورت سالم و بهداشتی در کشتی بمانند، مواجه هستند. من فکر می‌کنم این امر به نمایندگی از همه کسانی که در ماه‌های گذشته به شدت مبارزه کرده‌اند، بسیار مفید خواهد بود. اگر به هر نحوی در این روند بشردوستانه اختلال ایجاد شود، متأسفانه باید با آن اختلال به شدت برخورد شود.</text>
      <views>21509</views>
      <forwards>121</forwards>
      <media type="none"/>
    </post>
    <post id="45444">
      <date>2026-05-03T20:49:11.000Z</date>
      <text>🔴 ترامپ:

کشورهایی از سراسر جهان، که تقریباً هیچ‌کدام در مناقشات خاورمیانه که به این وضوح و خشونت، برای همه قابل مشاهده است، دخیل نیستند، از ایالات متحده درخواست کرده‌اند که آیا می‌توانیم به آزاد کردن کشتی‌هایشان که در تنگه هرمز گیر افتاده‌اند، کمک کنیم، کشتی‌هایی که مطلقاً هیچ ارتباطی با آنها ندارند - آنها صرفاً تماشاگران بی‌طرف و بی‌گناه هستند! برای خیر ایران، خاورمیانه و ایالات متحده، به این کشورها گفته‌ایم که کشتی‌هایشان را با خیال راحت از این آبراه‌های محدود شده خارج خواهیم کرد تا بتوانند آزادانه و با توانایی به کار خود ادامه دهند. باز هم، اینها کشتی‌هایی از مناطقی از جهان هستند که به هیچ وجه درگیر اتفاقاتی که در حال حاضر در خاورمیانه در حال رخ دادن است، نیستند. من به نمایندگانم گفته‌ام که به آنها اطلاع دهند که ما تمام تلاش خود را برای خروج ایمن کشتی‌ها و خدمه آنها از تنگه انجام خواهیم داد. در همه موارد، آنها گفته‌اند که تا زمانی که منطقه برای ناوبری و هر چیز دیگری امن نشود، باز نخواهند گشت. این فرآیند، پروژه آزادی، صبح دوشنبه به وقت خاورمیانه آغاز خواهد شد.</text>
      <views>21087</views>
      <forwards>137</forwards>
      <media type="photo" available="true">
        <file>img/chekhabarre__45444__photo.jpg</file>
        <width>979</width>
        <height>1280</height>
        <telegram_link>https://t.me/chekhabarre/45444</telegram_link>
      </media>
    </post>
    <post id="45443">
      <date>2026-05-03T19:50:48.000Z</date>
      <text></text>
      <views>21579</views>
      <forwards>101</forwards>
      <media type="photo" available="true">
        <file>img/chekhabarre__45443__photo.jpg</file>
        <width>1200</width>
        <height>800</height>
        <telegram_link>https://t.me/chekhabarre/45443</telegram_link>
      </media>
    </post>
    <post id="45442">
      <date>2026-05-03T19:50:47.000Z</date>
      <text></text>
      <views>21702</views>
      <forwards>102</forwards>
      <media type="photo" available="true">
        <file>img/chekhabarre__45442__photo.jpg</file>
        <width>1200</width>
        <height>800</height>
        <telegram_link>https://t.me/chekhabarre/45442</telegram_link>
      </media>
    </post>
  </posts>
</channel>